spotify2tidal/__init__.py
spotify2tidal/spotify.py
spotify2tidal/spotify2tidal.py
spotify2tidal/tidal.py
spotify2tidal-1.1.dist-info/LICENSE
spotify2tidal-1.1.dist-info/METADATA
spotify2tidal-1.1.dist-info/WHEEL
spotify2tidal-1.1.dist-info/top_level.txt
spotify2tidal-1.1.dist-info/RECORD
