Metadata-Version: 2.1
Name: spotify2tidal
Version: 1.1
Summary: "Copy Spotify playlists, saved albums/artists/tracks to Tidal"
Home-page: https://github.com/taschenb/spotify2tidal
Author: taschenb
Author-email: taschenb@posteo.de
License: GPLv3+
Keywords: spotify,tidal,discover weekly
Platform: UNKNOWN
Classifier: License :: OSI Approved :: GNU General Public License v3 or later (GPLv3+)
Classifier: Programming Language :: Python
Classifier: Programming Language :: Python :: 3
Classifier: Programming Language :: Python :: 3.4
Classifier: Programming Language :: Python :: 3.5
Classifier: Programming Language :: Python :: 3.6
Classifier: Programming Language :: Python :: 3.7
Requires-Dist: spotipy (>=2.4.4)
Requires-Dist: tidalapi (>=0.5.0)
Requires-Dist: requests (>=2.11.1)
